<?xml version="1.0" encoding="utf-8"?><Logical_EditPreset>   <list name="Version" type="list">      <item>         <string name="AppName" value="Cubase"/>         <int name="AppVersion" value="12"/>      </item>   </list>   <member name="Attributes">      <int name="VersionMagic" value="16384"/>      <member name="ExpertSetting">         <int name="Value" value="1"/>         <int name="Min" value="0"/>         <int name="Max" value="1"/>      </member>      <member name="Info">         <string name="s" value=""/>      </member>      <list name="Filter" type="obj">         <obj class="leToken" ID="105553120064192">            <int name="Digit" value="101"/>         </obj>         <obj class="lePositionTarget" ID="105553504125568">            <int name="Digit" value="100"/>            <int name="Type" value="206"/>            <int name="DomainType" value="0"/>            <obj class="LeUIntValue" name="Value1" ID="105553217136960">               <int name="Min" value="0"/>               <int name="Max" value="1920"/>               <int name="Value" value="460"/>            </obj>            <obj class="LeUIntValue" name="Value2" ID="105553217138160">               <int name="Min" value="0"/>               <int name="Max" value="1920"/>               <int name="Value" value="500"/>            </obj>         </obj>         <obj class="leToken" ID="105553120062960">            <int name="Digit" value="102"/>         </obj>      </list>      <member name="PostName">         <string name="s" value=""/>      </member>      <member name="processType">         <int name="Value" value="6"/>         <int name="Min" value="0"/>         <int name="Max" value="8"/>      </member>      <member name="Context">         <int name="Value" value="0"/>         <int name="Min" value="0"/>         <int name="Max" value="2"/>      </member>      <int name="VersionMagic12" value="4608"/>   </member>   <bin name="Preset">		0040000001000000000000000A0000000100000000000A000000010003000000		FEFFFFFF09000000436D4F626A656374000000FFFFFFFF080000006C65546F6B		656E0000000400000065000000FEFFFFFF120000006C65436F6E646974696F6E		546172676574000000FFFFFFFF110000006C65506F736974696F6E5461726765		740000006B00000064000000CE00000000000000FEFFFFFF0A00000055496E74		56616C7565000000FEFFFFFF070000005556616C7565000000FFFFFFFF0C0000		004C6555496E7456616C75650000000C0000000000000080070000CC010000B9		0000800C0000000000000080070000F401000033000080040000006600000000		000000060000000000000000000000001100000000000000000000   </bin></Logical_EditPreset>